[
  { "id": 1, "name": "Crunches", "area": "Upper", "level": 1, "img": "assets/img/exercises/crunches.jpg", "howto": "Lie on your back, knees bent; lift shoulders off the floor by contracting abs." },
  { "id": 2, "name": "Reverse Crunches", "area": "Lower", "level": 1, "img": "assets/img/exercises/reverse_crunches.jpg", "howto": "Lie on your back, lift legs and hips toward chest, curling lower abs." },
  { "id": 3, "name": "Flutter Kicks", "area": "Six-pack", "level": 1, "img": "assets/img/exercises/flutter_kicks.jpg", "howto": "Lie on back, lift legs slightly, and kick them up and down alternately." },
  { "id": 4, "name": "Sitting Twists", "area": "Obliques", "level": 1, "img": "assets/img/exercises/sitting_twists.jpg", "howto": "Sit with knees bent, lean back slightly, twist torso side to side." },
  { "id": 5, "name": "Knee to Elbow", "area": "Complete", "level": 1, "img": "assets/img/exercises/knee_to_elbow.jpg", "howto": "Lie back, bring opposite knee and elbow together in a crunching twist." },
  { "id": 6, "name": "Half Wipers", "area": "Core", "level": 1, "img": "assets/img/exercises/half_wipers.jpg", "howto": "Lie on back, arms out, legs raised; lower legs side-to-side in half arcs." },

  { "id": 7, "name": "High Crunches", "area": "Upper", "level": 2, "img": "assets/img/exercises/high_crunches.jpg", "howto": "Perform crunches with arms extended overhead while lifting shoulders." },
  { "id": 8, "name": "Scissors", "area": "Lower", "level": 2, "img": "assets/img/exercises/scissors.jpg", "howto": "Lie on back, alternate lifting one straight leg while lowering the other close to the floor." },
  { "id": 9, "name": "Elbow Plank", "area": "Six-pack", "level": 2, "img": "assets/img/exercises/elbow_plank.jpg", "howto": "Hold plank position resting on forearms, keeping body straight." },
  { "id": 10, "name": "Cross Crunches", "area": "Obliques", "level": 2, "img": "assets/img/exercises/cross_crunches.jpg", "howto": "Crunch while bringing shoulder toward opposite knee." },
  { "id": 11, "name": "Knee-to-Elbow v2", "area": "Complete", "level": 2, "img": "assets/img/exercises/knee_to_elbow_v2.jpg", "howto": "From plank, drive knee forward to touch elbow, keeping hips low." },
  { "id": 12, "name": "Arm / Leg Raises", "area": "Core", "level": 2, "img": "assets/img/exercises/arm_leg_raises.jpg", "howto": "From plank, raise opposite arm and leg simultaneously, hold briefly." },

  { "id": 13, "name": "Sit-ups", "area": "Upper", "level": 3, "img": "assets/img/exercises/sit_ups.jpg", "howto": "Lie back, knees bent; raise torso fully upright, then return down." },
  { "id": 14, "name": "Leg Raises", "area": "Lower", "level": 3, "img": "assets/img/exercises/leg_raises.jpg", "howto": "Lie flat, lift both straight legs up, lower slowly without touching the floor." },
  { "id": 15, "name": "L-sit", "area": "Six-pack", "level": 3, "img": "assets/img/exercises/l_sit.jpg", "howto": "Sit on floor, lift body with hands beside hips, keeping legs extended straight." },
  { "id": 16, "name": "Side Jack-knives", "area": "Obliques", "level": 3, "img": "assets/img/exercises/side_jack_knives.jpg", "howto": "Lie on side, lift legs and upper body together, crunching sideways." },
  { "id": 17, "name": "Dead Bug", "area": "Complete", "level": 3, "img": "assets/img/exercises/dead_bug.jpg", "howto": "Lie on back, extend opposite arm and leg while keeping lower back pressed down." },
  { "id": 18, "name": "Wipers", "area": "Core", "level": 3, "img": "assets/img/exercises/wipers.jpg", "howto": "Lie on back, arms out, legs raised; lower legs side-to-side in wide arcs." },

  { "id": 19, "name": "Long Arm Crunches", "area": "Upper", "level": 4, "img": "assets/img/exercises/long_arm_crunches.jpg", "howto": "Crunch with arms stretched straight behind head, moving with torso." },
  { "id": 20, "name": "Pulse-ups", "area": "Lower", "level": 4, "img": "assets/img/exercises/pulse_ups.jpg", "howto": "Legs raised, push hips upward using lower abs in small controlled pulses." },
  { "id": 21, "name": "Star Plank", "area": "Six-pack", "level": 4, "img": "assets/img/exercises/star_plank.jpg", "howto": "Side plank with top leg and arm raised, forming a star shape." },
  { "id": 22, "name": "Toe Taps", "area": "Obliques", "level": 4, "img": "assets/img/exercises/toe_taps.jpg", "howto": "Lie back, knees bent, lift shoulders, reach alternate hands to opposite toes." },
  { "id": 23, "name": "Plank Crunches", "area": "Complete", "level": 4, "img": "assets/img/exercises/plank_crunches.jpg", "howto": "From plank, draw knees toward chest one at a time." },
  { "id": 24, "name": "Plank Rolls", "area": "Core", "level": 4, "img": "assets/img/exercises/plank_rolls.jpg", "howto": "Elbow plank, roll hips side to side toward floor." },

  { "id": 25, "name": "Hundreds", "area": "Upper", "level": 5, "img": "assets/img/exercises/hundreds.jpg", "howto": "Lie on back, legs raised; pump arms up and down while holding core tight." },
  { "id": 26, "name": "Bicycle Crunches", "area": "Lower", "level": 5, "img": "assets/img/exercises/bicycle_crunches.jpg", "howto": "Crunch while bringing opposite elbow to opposite knee, pedaling legs." },
  { "id": 27, "name": "Hollow Hold", "area": "Six-pack", "level": 5, "img": "assets/img/exercises/hollow_hold.jpg", "howto": "Lie on back, lift shoulders and legs off floor, lower back pressed down." },
  { "id": 28, "name": "Sitting Punches", "area": "Obliques", "level": 5, "img": "assets/img/exercises/sitting_punches.jpg", "howto": "Sit leaning back, core engaged, punch fists alternately across body." },
  { "id": 29, "name": "Side Plank Crunches", "area": "Complete", "level": 5, "img": "assets/img/exercises/side_plank_crunches.jpg", "howto": "Side plank with top knee pulling toward chest as you crunch." },
  { "id": 30, "name": "Knee-in Twists", "area": "Core", "level": 5, "img": "assets/img/exercises/knee_in_twists.jpg", "howto": "From seated lean-back, draw both knees in then twist side-to-side." },

  { "id": 31, "name": "Knee Crunches", "area": "Upper", "level": 6, "img": "assets/img/exercises/knee_crunches.jpg", "howto": "Crunch while pulling knees in toward chest simultaneously." },
  { "id": 32, "name": "Crunch Kicks", "area": "Lower", "level": 6, "img": "assets/img/exercises/crunch_kicks.jpg", "howto": "Lying down, extend legs outward, then pull them back in with a crunch." },
  { "id": 33, "name": "V-ups", "area": "Six-pack", "level": 6, "img": "assets/img/exercises/v_ups.jpg", "howto": "Lie flat, lift legs and torso simultaneously to form a 'V', reaching hands to feet." },
  { "id": 34, "name": "Side Plank", "area": "Obliques", "level": 6, "img": "assets/img/exercises/side_plank.jpg", "howto": "Support body on one arm’s side, hold a straight line position." },
  { "id": 35, "name": "V with Rotations", "area": "Complete", "level": 6, "img": "assets/img/exercises/v_with_rotations.jpg", "howto": "Do a V-up, but twist torso at top to target obliques." },
  { "id": 36, "name": "Climber Taps", "area": "Core", "level": 6, "img": "assets/img/exercises/climber_taps.jpg", "howto": "From plank, drive knee in and tap opposite elbow." }
]
